paperank/__init__.py
paperank/citation_crawler.py
paperank/citation_matrix.py
paperank/crossref.py
paperank/doi_utils.py
paperank/open_citations.py
paperank/paperank_core.py
paperank/paperank_matrix.py
paperank/types.py
paperank-0.3.0.dist-info/licenses/LICENSE
paperank-0.3.0.dist-info/METADATA
paperank-0.3.0.dist-info/WHEEL
paperank-0.3.0.dist-info/top_level.txt
paperank-0.3.0.dist-info/RECORD
