Metadata-Version: 2.4
Name: paperank
Version: 0.3.0
Summary: A publication ranking and citation network analysis tools.
Author-email: Roberto Rossi <robros@gmail.com>
License: MIT
Project-URL: Homepage, https://github.com/gwr3n/paperank
Classifier: Programming Language :: Python :: 3
Classifier: Programming Language :: Python :: 3 :: Only
Classifier: Programming Language :: Python :: 3.9
Classifier: Programming Language :: Python :: 3.10
Classifier: Programming Language :: Python :: 3.11
Classifier: Programming Language :: Python :: 3.12
Requires-Python: >=3.9
License-File: LICENSE
Requires-Dist: numpy>=1.21
Requires-Dist: scipy>=1.7
Requires-Dist: requests>=2.25
Requires-Dist: tqdm>=4.62
Requires-Dist: urllib3<3,>=1.26
Dynamic: license-file
